melonapi/__init__.py
melonapi/melonapi.py
melonapi/scrapeMelon.py
melonapi/spotify.py
melonapi-0.0.2.dist-info/LICENSE
melonapi-0.0.2.dist-info/METADATA
melonapi-0.0.2.dist-info/WHEEL
melonapi-0.0.2.dist-info/top_level.txt
melonapi-0.0.2.dist-info/RECORD
