Metadata-Version: 2.1
Name: melonapi
Version: 0.0.2
Summary: A small Melon api
Home-page: https://github.com/ko28/melon-api/
Author: Daniel Ko
Author-email: danielhbko@gmail.com
License: UNKNOWN
Platform: UNKNOWN
Classifier: Programming Language :: Python :: 3
Classifier: License :: OSI Approved :: MIT License
Classifier: Operating System :: OS Independent
Requires-Python: >=3.6
Requires-Dist: Flask
Requires-Dist: requests
Requires-Dist: lxml
Requires-Dist: beautifulsoup4
